{
    "type": "FeatureCollection",
    "name": "JPT_KOD_JE_3026",
    "features": [
        {
            "type": "Feature",
            "properties": {
                "JPT_KOD_JE": "3026",
                "JPT_NAZWA_": "powiat śremski",
                "id": 83,
                "ksiega": 388424,
                "id zoz": 475263,
                "id jednostki": "763299",
                "id komórki": 6681490,
                "regon": 30177867200048,
                "kod jednostki": "01",
                "kod komórki": 1,
                "specjalnosc": "Szpitalny oddział ratunkowy",
                "kodresortviii": 4902,
                "nazwa": "Szpitalny Oddział Ratunkowy",
                "teryt opis": "Śrem - miasto",
                "ulica": "ul. Józefa Chełmońskiego",
                "budynek": ".1",
                "lokal": "NULL",
                "kod": "63-100",
                "miejscowosc": "Śrem",
                "teryt": 3026044,
                "kod simc": 971560,
                "kod ulicy": "02706",
                "lozka": 8,
                "liczba łóżek iom": 1,
                "liczba łóżek ink": 0,
                "liczba łóżek now": 0,
                "liczba inkubatorów": 0,
                "liczba dializ": 0,
                "liczba łóżek": 0,
                "data rozpoczęcia działalności komórki": "2012-01-01"
            },
            "geometry": {
                "type": "Point",
                "coordinates": [
                    17.00629342924304,
                    52.089395582687004
                ]
            }
        }
    ]
}