{
    "type": "FeatureCollection",
    "name": "JPT_KOD_JE_2465",
    "features": [
        {
            "type": "Feature",
            "properties": {
                "name": "Szpitalny Oddział Ratunkowy (Sor)",
                "local:ref": "13",
                "emergency": "yes",
                "healthcare": "emergency_ward"
            },
            "geometry": {
                "type": "Point",
                "coordinates": [
                    19.17671910929001,
                    50.320141733137184
                ]
            }
        }
    ]
}