{
    "type": "FeatureCollection",
    "name": "JPT_KOD_JE_0808",
    "features": [
        {
            "type": "Feature",
            "properties": {
                "name": "Szpitalny Oddział Ratunkowy",
                "local:ref": "6",
                "emergency": "yes",
                "healthcare": "emergency_ward"
            },
            "geometry": {
                "type": "Point",
                "coordinates": [
                    15.534728577059752,
                    52.25230639708542
                ]
            }
        }
    ]
}