{
    "type": "FeatureCollection",
    "name": "JPT_KOD_JE_1601",
    "features": [
        {
            "type": "Feature",
            "properties": {
                "name": "Szpitalny Oddział Ratunkowy",
                "local:ref": "1",
                "emergency": "yes",
                "healthcare": "emergency_ward"
            },
            "geometry": {
                "type": "Point",
                "coordinates": [
                    17.477238006345114,
                    50.85754590985775
                ]
            }
        }
    ]
}