{
    "type": "FeatureCollection",
    "name": "JPT_KOD_JE_2463",
    "features": [
        {
            "type": "Feature",
            "properties": {
                "name": "Szpitalny Oddział Ratunkowy",
                "local:ref": "7",
                "emergency": "yes",
                "healthcare": "emergency_ward"
            },
            "geometry": {
                "type": "Point",
                "coordinates": [
                    18.94841684051104,
                    50.29678016845741
                ]
            }
        }
    ]
}