{
    "type": "FeatureCollection",
    "name": "JPT_KOD_JE_1608",
    "features": [
        {
            "type": "Feature",
            "properties": {
                "name": "Szpitalny Oddział Ratunkowy",
                "local:ref": "1",
                "emergency": "yes",
                "healthcare": "emergency_ward"
            },
            "geometry": {
                "type": "Point",
                "coordinates": [
                    18.41352859664999,
                    50.88060208605476
                ]
            }
        }
    ]
}