{
    "type": "FeatureCollection",
    "name": "JPT_KOD_JE_1413",
    "features": [
        {
            "type": "Feature",
            "properties": {
                "name": "Szpitalny Oddział Ratunkowy",
                "local:ref": "1",
                "emergency": "yes",
                "healthcare": "emergency_ward"
            },
            "geometry": {
                "type": "Point",
                "coordinates": [
                    20.371170841919046,
                    53.12341599146512
                ]
            }
        }
    ]
}