{
    "type": "FeatureCollection",
    "name": "JPT_KOD_JE_2464",
    "features": [
        {
            "type": "Feature",
            "properties": {
                "name": "Szpitalny Oddział Ratunkowy",
                "local:ref": "104",
                "emergency": "yes",
                "healthcare": "emergency_ward"
            },
            "geometry": {
                "type": "Point",
                "coordinates": [
                    19.08917200000003,
                    50.82962200001371
                ]
            }
        },
        {
            "type": "Feature",
            "properties": {
                "name": "Szpitalny Oddział Ratunkowy",
                "local:ref": "15",
                "emergency": "yes",
                "healthcare": "emergency_ward"
            },
            "geometry": {
                "type": "Point",
                "coordinates": [
                    19.133279480311042,
                    50.81186500546005
                ]
            }
        }
    ]
}