{
    "type": "FeatureCollection",
    "name": "JPT_KOD_JE_0407",
    "features": [
        {
            "type": "Feature",
            "properties": {
                "name": "Szpitalny Oddział Ratunkowy",
                "local:ref": "97",
                "emergency": "yes",
                "healthcare": "emergency_ward"
            },
            "geometry": {
                "type": "Point",
                "coordinates": [
                    18.26278094034124,
                    52.78176339133269
                ]
            }
        }
    ]
}