{
    "type": "FeatureCollection",
    "name": "JPT_KOD_JE_0615",
    "features": [
        {
            "type": "Feature",
            "properties": {
                "name": "Szpitalny Oddział Ratunkowy",
                "local:ref": "111",
                "emergency": "yes",
                "healthcare": "emergency_ward"
            },
            "geometry": {
                "type": "Point",
                "coordinates": [
                    22.606243655026105,
                    51.77195836638497
                ]
            }
        }
    ]
}