{
    "type": "FeatureCollection",
    "name": "JPT_KOD_JE_2607",
    "features": [
        {
            "type": "Feature",
            "properties": {
                "name": "Szpitalny Oddział Ratunkowy",
                "local:ref": "11",
                "emergency": "yes",
                "healthcare": "emergency_ward"
            },
            "geometry": {
                "type": "Point",
                "coordinates": [
                    21.36124886807919,
                    50.95287243955221
                ]
            }
        }
    ]
}