{
    "type": "FeatureCollection",
    "name": "JPT_KOD_JE_1818",
    "features": [
        {
            "type": "Feature",
            "properties": {
                "name": "Szpitalny Oddział Ratunkowy",
                "local:ref": "4.",
                "emergency": "yes",
                "healthcare": "emergency_ward"
            },
            "geometry": {
                "type": "Point",
                "coordinates": [
                    22.068824898981113,
                    50.563298190767156
                ]
            }
        }
    ]
}