{
    "type": "FeatureCollection",
    "name": "JPT_KOD_JE_1607",
    "features": [
        {
            "type": "Feature",
            "properties": {
                "name": "Oddział Ratunkowy",
                "local:ref": "23",
                "emergency": "yes",
                "healthcare": "emergency_ward"
            },
            "geometry": {
                "type": "Point",
                "coordinates": [
                    17.329248268345008,
                    50.47139063461616
                ]
            }
        }
    ]
}