{
    "type": "FeatureCollection",
    "name": "JPT_KOD_JE_2261",
    "features": [
        {
            "type": "Feature",
            "properties": {
                "JPT_KOD_JE": "2261",
                "JPT_NAZWA_": "powiat Gdańsk",
                "id": 218,
                "ksiega": 392266,
                "id zoz": 482414,
                "id jednostki": "NULL",
                "id komórki": 6865133,
                "regon": 28864000090,
                "kod jednostki": "NULL",
                "kod komórki": 110,
                "specjalnosc": "Szpitalny oddział ratunkowy",
                "kodresortviii": 4902,
                "nazwa": "Kliniczny Oddział Ratunkowy",
                "teryt opis": "Gdańsk - gmina miejska",
                "ulica": "ul. Mariana Smoluchowskiego",
                "budynek": "17",
                "lokal": "NULL",
                "kod": "80-214",
                "miejscowosc": "Gdańsk",
                "teryt": 2261011,
                "kod simc": 933016,
                "kod ulicy": "20372",
                "lozka": 16,
                "liczba łóżek iom": 4,
                "liczba łóżek ink": 0,
                "liczba łóżek now": 0,
                "liczba inkubatorów": 0,
                "liczba dializ": 0,
                "liczba łóżek": 0,
                "data rozpoczęcia działalności komórki": "2001-04-09"
            },
            "geometry": {
                "type": "Point",
                "coordinates": [
                    18.619570433114653,
                    54.365903862743934
                ]
            }
        },
        {
            "type": "Feature",
            "properties": {
                "JPT_KOD_JE": "2261",
                "JPT_NAZWA_": "powiat Gdańsk",
                "id": 136,
                "ksiega": 390834,
                "id zoz": 479298,
                "id jednostki": "771700",
                "id komórki": 6770951,
                "regon": 22196438500032,
                "kod jednostki": "01",
                "kod komórki": 127,
                "specjalnosc": "Szpitalny oddział ratunkowy",
                "kodresortviii": 4902,
                "nazwa": "Szpitalny oddział ratunkowy",
                "teryt opis": "Gdańsk - gmina miejska",
                "ulica": "ul. Nowe Ogrody",
                "budynek": "1-6",
                "lokal": "NULL",
                "kod": "80-803",
                "miejscowosc": "Gdańsk",
                "teryt": 2261011,
                "kod simc": 933016,
                "kod ulicy": "14370",
                "lozka": 22,
                "liczba łóżek iom": 2,
                "liczba łóżek ink": 0,
                "liczba łóżek now": 0,
                "liczba inkubatorów": 0,
                "liczba dializ": 0,
                "liczba łóżek": 0,
                "data rozpoczęcia działalności komórki": "2012-02-01"
            },
            "geometry": {
                "type": "Point",
                "coordinates": [
                    18.612421999999814,
                    54.403158000019445
                ]
            }
        },
        {
            "type": "Feature",
            "properties": {
                "JPT_KOD_JE": "2261",
                "JPT_NAZWA_": "powiat Gdańsk",
                "id": 137,
                "ksiega": 390834,
                "id zoz": 479298,
                "id jednostki": "771703",
                "id komórki": 6771000,
                "regon": 22196438500032,
                "kod jednostki": "04",
                "kod komórki": 174,
                "specjalnosc": "Szpitalny oddział ratunkowy",
                "kodresortviii": 4902,
                "nazwa": "Szpitalny Oddział Ratunkowy",
                "teryt opis": "Gdańsk - gmina miejska",
                "ulica": "al. Jana Pawła II",
                "budynek": "50",
                "lokal": "NULL",
                "kod": "80-462",
                "miejscowosc": "Gdańsk",
                "teryt": 2261011,
                "kod simc": 933016,
                "kod ulicy": "07120",
                "lozka": 12,
                "liczba łóżek iom": 3,
                "liczba łóżek ink": 0,
                "liczba łóżek now": 0,
                "liczba inkubatorów": 0,
                "liczba dializ": 0,
                "liczba łóżek": 0,
                "data rozpoczęcia działalności komórki": "2001-01-01"
            },
            "geometry": {
                "type": "Point",
                "coordinates": [
                    18.612421999999814,
                    54.403158000019445
                ]
            }
        }
    ]
}
