{
    "type": "FeatureCollection",
    "name": "JPT_KOD_JE_2261",
    "features": [
        {
            "type": "Feature",
            "properties": {
                "name": "Kliniczny Oddział Ratunkowy",
                "local:ref": "17",
                "emergency": "yes",
                "healthcare": "emergency_ward"
            },
            "geometry": {
                "type": "Point",
                "coordinates": [
                    18.619570433114653,
                    54.365903862743934
                ]
            }
        },
        {
            "type": "Feature",
            "properties": {
                "name": "Szpitalny Oddział Ratunkowy",
                "local:ref": "1-6",
                "emergency": "yes",
                "healthcare": "emergency_ward"
            },
            "geometry": {
                "type": "Point",
                "coordinates": [
                    18.612421999999814,
                    54.403158000019445
                ]
            }
        },
        {
            "type": "Feature",
            "properties": {
                "name": "Szpitalny Oddział Ratunkowy",
                "local:ref": "50",
                "emergency": "yes",
                "healthcare": "emergency_ward"
            },
            "geometry": {
                "type": "Point",
                "coordinates": [
                    18.612421999999814,
                    54.403158000019445
                ]
            }
        }
    ]
}