{
    "type": "FeatureCollection",
    "name": "JPT_KOD_JE_2264",
    "features": [
        {
            "type": "Feature",
            "properties": {
                "_uid_": 172,
                "JPT_KOD_JE": "2264",
                "JPT_NAZWA_": "powiat Sopot",
                "id": 550,
                "wojewodztwo": "pomorskie",
                "miasto": "Sopot",
                "powiat": "Sopot",
                "adres": "Grunwaldzka 1-3",
                "miejscowosc": "Sopot",
                "kod": "81-759",
                "nazwa": "Wojewódzki Zespół Reumatologiczny im. dr Jadwigi Titz-Kosko",
                "poziom": "II stopień",
                "www": "http://www.wzr.com.pl",
                "telefon": "58 555-75-20",
                "e-mail": null
            },
            "geometry": {
                "type": "Point",
                "coordinates": [
                    18.56943774146916,
                    54.44475539854972
                ]
            }
        }
    ]
}