{
    "type": "FeatureCollection",
    "name": "JPT_KOD_JE_1204",
    "features": [
        {
            "type": "Feature",
            "properties": {
                "_uid_": 368,
                "JPT_KOD_JE": "1204",
                "JPT_NAZWA_": "powiat dąbrowski",
                "id": 176,
                "wojewodztwo": "małopolskie",
                "miasto": "Dąbrowa Tarnowska",
                "powiat": "dąbrowski",
                "adres": "Szpitalna 1",
                "miejscowosc": "Dąbrowa Tarnowska",
                "kod": "33-200",
                "nazwa": "ZESPÓŁ OPIEKI ZDROWOTNEJ W DĄBROWIE TARNOWSKIEJ",
                "poziom": "I stopień",
                "www": "http://www.zozdt.pl",
                "telefon": "14 64 22 831",
                "e-mail": null
            },
            "geometry": {
                "type": "Point",
                "coordinates": [
                    20.975809566753693,
                    50.17717121866438
                ]
            }
        }
    ]
}