{
    "type": "FeatureCollection",
    "name": "JPT_KOD_JE_0808",
    "crs": {
        "type": "name",
        "properties": {
            "name": "urn:ogc:def:crs:EPSG::4326"
        }
    },
    "features": [
        {
            "type": "Feature",
            "properties": {
                "_uid_": 225,
                "JPT_KOD_JE": "0808",
                "JPT_NAZWA_": "powiat świebodziński",
                "id": 98,
                "wojewodztwo": "lubuskie",
                "miasto": "Świebodzin",
                "powiat": "świebodziński",
                "adres": "Młyńska 6",
                "miejscowosc": "Świebodzin",
                "kod": "66-200",
                "nazwa": "Nowy Szpital w Świebodzinie Spółka z ograniczoną odpowiedzialnością",
                "poziom": "I stopień",
                "www": "http://www.nowyszpital.pl",
                "telefon": "68 456 40 01",
                "e-mail": "swiebodzin@nowyszpital.pl"
            },
            "geometry": {
                "type": "Point",
                "coordinates": [
                    15.534728176632845,
                    52.25230639971419
                ]
            }
        },
        {
            "type": "Feature",
            "properties": {
                "_uid_": 226,
                "JPT_KOD_JE": "0808",
                "JPT_NAZWA_": "powiat świebodziński",
                "id": 101,
                "wojewodztwo": "lubuskie",
                "miasto": "Świebodzin",
                "powiat": "świebodziński",
                "adres": "Zamkowa 1",
                "miejscowosc": "Świebodzin",
                "kod": "66-200",
                "nazwa": "Lubuskie Centrum Ortopedii im. dr. Lecha Wierusza Spółka z ograniczoną odpowiedzialnością",
                "poziom": "II stopień",
                "www": "http://www.loro.pl",
                "telefon": "68 475 06 01",
                "e-mail": "sekretariat@loro.pl"
            },
            "geometry": {
                "type": "Point",
                "coordinates": [
                    15.535030267663,
                    52.250444718738684
                ]
            }
        }
    ]
}