{
    "type": "FeatureCollection",
    "name": "JPT_KOD_JE_1864",
    "crs": {
        "type": "name",
        "properties": {
            "name": "urn:ogc:def:crs:EPSG::4326"
        }
    },
    "features": [
        {
            "type": "Feature",
            "properties": {
                "_uid_": 301,
                "JPT_KOD_JE": "1864",
                "JPT_NAZWA_": "powiat Tarnobrzeg",
                "id": 310,
                "wojewodztwo": "podkarpackie",
                "miasto": "Tarnobrzeg",
                "powiat": "m. Tarnobrzeg ",
                "adres": "Szpitalna 1",
                "miejscowosc": "Tarnobrzeg",
                "kod": "39-400 ",
                "nazwa": "WOJEWÓDZKI SZPITAL IM.ZOFII Z ZAMOYSKICH TARNOWSKIEJ W TARNOBRZEGU",
                "poziom": "II stopień",
                "www": "http://szpitaltbg.pl",
                "telefon": "15 81 23 001",
                "e-mail": null
            },
            "geometry": {
                "type": "Point",
                "coordinates": [
                    21.67049985125104,
                    50.56687271347095
                ]
            }
        }
    ]
}