{
    "type": "FeatureCollection",
    "name": "JPT_KOD_JE_1437",
    "crs": {
        "type": "name",
        "properties": {
            "name": "urn:ogc:def:crs:EPSG::4326"
        }
    },
    "features": [
        {
            "type": "Feature",
            "properties": {
                "_uid_": 220,
                "JPT_KOD_JE": "1437",
                "JPT_NAZWA_": "powiat żuromiński",
                "id": 216,
                "wojewodztwo": "mazowieckie",
                "miasto": "ŻUROMIN",
                "powiat": "ŻUROMIŃSKI",
                "adres": "SZPITALNA 56",
                "miejscowosc": "ŻUROMIN ",
                "kod": null,
                "nazwa": "SAMODZIELNY PUBLICZNY ZESPÓŁ ZAKŁADÓW OPIEKI ZDROWOTNEJ W ŻUROMINIE",
                "poziom": "I stopień",
                "www": "http://www.szpital-zuromin.pl",
                "telefon": "23 657-22-01",
                "e-mail": "sekretariat@szpital-zuromin.pl"
            },
            "geometry": {
                "type": "Point",
                "coordinates": [
                    19.919077077286424,
                    53.07027181667636
                ]
            }
        }
    ]
}