{
    "type": "FeatureCollection",
    "name": "JPT_KOD_JE_1820",
    "crs": {
        "type": "name",
        "properties": {
            "name": "urn:ogc:def:crs:EPSG::4326"
        }
    },
    "features": [
        {
            "type": "Feature",
            "properties": {
                "_uid_": 352,
                "JPT_KOD_JE": "1820",
                "JPT_NAZWA_": "powiat tarnobrzeski",
                "id": 301,
                "wojewodztwo": "podkarpackie",
                "miasto": "Nowa Dęba",
                "powiat": "tarnobrzeski ",
                "adres": "Marii Skłodowskiej-Curie 1A",
                "miejscowosc": "Nowa Dęba",
                "kod": "39-460 ",
                "nazwa": "SAMODZIELNY PUBLICZNY ZESPÓŁ ZAKŁADÓW OPIEKI ZDROWOTNEJ W NOWEJ DĘBIE",
                "poziom": "I stopień",
                "www": "http://zoznowadeba.pl",
                "telefon": "(015)846 26 51",
                "e-mail": null
            },
            "geometry": {
                "type": "Point",
                "coordinates": [
                    21.755603773578944,
                    50.419706681767565
                ]
            }
        }
    ]
}