{
    "type": "FeatureCollection",
    "name": "JPT_KOD_JE_1012",
    "crs": {
        "type": "name",
        "properties": {
            "name": "urn:ogc:def:crs:EPSG::4326"
        }
    },
    "features": [
        {
            "type": "Feature",
            "properties": {
                "_uid_": 444,
                "JPT_KOD_JE": "1012",
                "JPT_NAZWA_": "powiat radomszczański",
                "id": 128,
                "wojewodztwo": "łódzkie",
                "miasto": "Radomsko",
                "powiat": "radomszczański",
                "adres": "Jagiellońska 36",
                "miejscowosc": null,
                "kod": null,
                "nazwa": "Szpital Powiatowy w Radomsku",
                "poziom": "II stopień",
                "www": "http://www.szpital.biz.pl",
                "telefon": "44 681 08 00",
                "e-mail": "sekretariat@szpital.biz.pl"
            },
            "geometry": {
                "type": "Point",
                "coordinates": [
                    19.458766791087108,
                    51.05685794550544
                ]
            }
        }
    ]
}