{
    "type": "FeatureCollection",
    "name": "JPT_KOD_JE_2004",
    "crs": {
        "type": "name",
        "properties": {
            "name": "urn:ogc:def:crs:EPSG::4326"
        }
    },
    "features": [
        {
            "type": "Feature",
            "properties": {
                "_uid_": 318,
                "JPT_KOD_JE": "2004",
                "JPT_NAZWA_": "powiat grajewski",
                "id": 564,
                "wojewodztwo": "podlaskie",
                "miasto": "grajewski",
                "powiat": "Grajewo",
                "adres": "Konstytucji 3 Maja 34",
                "miejscowosc": "Grajewo",
                "kod": "19-200",
                "nazwa": "SZPITAL OGÓLNY IM. DR W. GINELA W GRAJEWIE",
                "poziom": "I stopień",
                "www": "http://www.szpital-grajewo.pl",
                "telefon": "86 272 32 71",
                "e-mail": null
            },
            "geometry": {
                "type": "Point",
                "coordinates": [
                    22.46980470272606,
                    53.6463365596205
                ]
            }
        }
    ]
}