{
    "type": "FeatureCollection",
    "name": "JPT_KOD_JE_1428",
    "features": [
        {
            "type": "Feature",
            "properties": {
                "name": "Zespół Opieki Zdrowotnej \"Szpitala Powiatowego\" W Sochaczewie",
                "website": "http://www.szpitalsochaczew.pl",
                "phone": "46 864-95-00",
                "email": "kancelaria@szpitalsochaczew.pl",
                "amenity": "hospital",
                "emergency": "yes",
                "healthcare": "hospital"
            },
            "geometry": {
                "type": "Point",
                "coordinates": [
                    20.22668801272006,
                    52.23908324667542
                ]
            }
        }
    ]
}