{
    "type": "FeatureCollection",
    "name": "JPT_KOD_JE_1802",
    "features": [
        {
            "type": "Feature",
            "properties": {
                "name": "Szpital Specjalistyczny W Brzozowie Podkarpacki Ośrodek Onkologiczny Im.Ks.B.Markiewicza",
                "website": "http://szpital-brzozow.pl",
                "phone": "(013)430 95 52",
                "amenity": "hospital",
                "emergency": "yes",
                "healthcare": "hospital"
            },
            "geometry": {
                "type": "Point",
                "coordinates": [
                    22.024631986176654,
                    49.69255572377262
                ]
            }
        }
    ]
}