{
    "type": "FeatureCollection",
    "name": "JPT_KOD_JE_1003",
    "features": [
        {
            "type": "Feature",
            "properties": {
                "name": "Centrum Dializa Sp. Z O.O.",
                "website": "http://www.szpitalwlasku.pl",
                "phone": "43 675 55 55",
                "email": "sekretariat@szpitalwlasku.pl",
                "amenity": "hospital",
                "emergency": "yes",
                "healthcare": "hospital"
            },
            "geometry": {
                "type": "Point",
                "coordinates": [
                    19.153133171247333,
                    51.59110511915366
                ]
            }
        }
    ]
}