{
    "type": "FeatureCollection",
    "name": "JPT_KOD_JE_2004",
    "features": [
        {
            "type": "Feature",
            "properties": {
                "name": "Szpital Ogólny Im. Dr W. Ginela W Grajewie",
                "website": "http://www.szpital-grajewo.pl",
                "phone": "86 272 32 71",
                "amenity": "hospital",
                "emergency": "yes",
                "healthcare": "hospital"
            },
            "geometry": {
                "type": "Point",
                "coordinates": [
                    22.46980470272606,
                    53.6463365596205
                ]
            }
        }
    ]
}