{
    "type": "FeatureCollection",
    "name": "JPT_KOD_JE_2006",
    "features": [
        {
            "type": "Feature",
            "properties": {
                "name": "Szpital Ogólny W Kolnie",
                "website": "http://www.szpitalkolno.pl",
                "phone": "86 278 23 50",
                "amenity": "hospital",
                "emergency": "yes",
                "healthcare": "hospital"
            },
            "geometry": {
                "type": "Point",
                "coordinates": [
                    21.921814686820404,
                    53.41228325715749
                ]
            }
        }
    ]
}