{
    "type": "FeatureCollection",
    "name": "JPT_KOD_JE_1435",
    "features": [
        {
            "type": "Feature",
            "properties": {
                "name": "Samodzielny Publiczny Zespół Zakładów Opieki Zdrowotnej W Wyszkowie",
                "website": "http://www.szpital-wyszkow.com.pl",
                "phone": "29 743-76-11",
                "email": "spzzoz@wp.pl",
                "amenity": "hospital",
                "emergency": "yes",
                "healthcare": "hospital"
            },
            "geometry": {
                "type": "Point",
                "coordinates": [
                    21.444838558499377,
                    52.586819733666324
                ]
            }
        }
    ]
}