{
    "type": "FeatureCollection",
    "name": "JPT_KOD_JE_2605",
    "features": [
        {
            "type": "Feature",
            "properties": {
                "name": "Zespół Opieki Zdrowotnej W Końskich",
                "website": "http://zoz.konskie.pl",
                "phone": "41 36 71 555 (444, 222)",
                "amenity": "hospital",
                "emergency": "yes",
                "healthcare": "hospital"
            },
            "geometry": {
                "type": "Point",
                "coordinates": [
                    20.391652370597104,
                    51.190851884042026
                ]
            }
        }
    ]
}