{
    "type": "FeatureCollection",
    "name": "JPT_KOD_JE_0804",
    "features": [
        {
            "type": "Feature",
            "properties": {
                "name": "Wielospecjalistyczny Szpital Samodzielny Publiczny Zakład Opieki Zdrowotnej W Nowej Soli",
                "website": "http://www.szpital-nowasol.pl",
                "phone": "68 388 21 00",
                "email": "sekretariat@szpital-nowasol.pl",
                "amenity": "hospital",
                "emergency": "yes",
                "healthcare": "hospital"
            },
            "geometry": {
                "type": "Point",
                "coordinates": [
                    15.68770778282012,
                    51.806987749793755
                ]
            }
        },
        {
            "type": "Feature",
            "properties": {
                "name": "Medinet Spółka Z Ograniczona Odpowiedzialnością",
                "website": "http://www.medinet.pl",
                "phone": "68 388 21 91",
                "email": "nowasol@medinet.pl",
                "amenity": "hospital",
                "emergency": "yes",
                "healthcare": "hospital"
            },
            "geometry": {
                "type": "Point",
                "coordinates": [
                    15.68770778282012,
                    51.806987749793755
                ]
            }
        }
    ]
}