{
    "type": "FeatureCollection",
    "name": "JPT_KOD_JE_0614",
    "features": [
        {
            "type": "Feature",
            "properties": {
                "name": "Samodzielny Publiczny Zakład Opieki Zdrowotnej W Puławach",
                "website": "http://www.szpitalpulawy.pl",
                "phone": "81 450 22 74, 450 22 77",
                "amenity": "hospital",
                "emergency": "yes",
                "healthcare": "hospital"
            },
            "geometry": {
                "type": "Point",
                "coordinates": [
                    21.97507376006144,
                    51.42190106971029
                ]
            }
        }
    ]
}