{
    "type": "FeatureCollection",
    "name": "JPT_KOD_JE_1424",
    "features": [
        {
            "type": "Feature",
            "properties": {
                "name": "Szpital Powiatowy Gajda-Med Spółka Z Ograniczoną Odpowiedzialnością",
                "website": "http://www.szpital.pultusk.pl",
                "phone": "236919901",
                "email": "sekretariat@szpital.pultusk.pl",
                "amenity": "hospital",
                "emergency": "yes",
                "healthcare": "hospital"
            },
            "geometry": {
                "type": "Point",
                "coordinates": [
                    21.114122333317972,
                    52.69373334326615
                ]
            }
        }
    ]
}