{
    "type": "FeatureCollection",
    "name": "JPT_KOD_JE_3026",
    "features": [
        {
            "type": "Feature",
            "properties": {
                "name": "Szpital Powiatowy Im. Tadeusza Malińskiego W Śremie Spółka Z Ograniczoną Odpowiedzialnością",
                "website": "http://www.szpitalwsremie.pl/ ",
                "phone": "(061)28-15-443 ",
                "amenity": "hospital",
                "emergency": "yes",
                "healthcare": "hospital"
            },
            "geometry": {
                "type": "Point",
                "coordinates": [
                    17.00629367281456,
                    52.0893952288127
                ]
            }
        },
        {
            "type": "Feature",
            "properties": {
                "name": "Wielkopolski Ośrodek Reumatologiczny Samodzielny Publiczny Specjalistyczny Zespół Opieki Zdrowotnej W Śremie",
                "website": "http://www.reumatologia.srem.net ",
                "phone": "(61)28-36-273, (61)28-36-289 ",
                "amenity": "hospital",
                "emergency": "yes",
                "healthcare": "hospital"
            },
            "geometry": {
                "type": "Point",
                "coordinates": [
                    17.025379609663226,
                    52.08447979041185
                ]
            }
        }
    ]
}