{
    "type": "FeatureCollection",
    "name": "JPT_KOD_JE_2606",
    "features": [
        {
            "type": "Feature",
            "properties": {
                "name": "\"Centrum Dializa\" Sp. Z O.O.",
                "website": "http://szpitalwopatowie.pl",
                "phone": "15 867 04 01",
                "amenity": "hospital",
                "emergency": "yes",
                "healthcare": "hospital"
            },
            "geometry": {
                "type": "Point",
                "coordinates": [
                    21.425167006855837,
                    50.80425805369838
                ]
            }
        }
    ]
}