{
    "type": "FeatureCollection",
    "name": "JPT_KOD_JE_1425",
    "features": [
        {
            "type": "Feature",
            "properties": {
                "name": "Samodzielny Publiczny Zespół Zakładów Opieki Zdrowotnej - Szpital W Iłży",
                "website": "http://www.szpitalilza.com.pl",
                "phone": "48-6163175",
                "email": "szrilza@szpitalilza.com.pl",
                "amenity": "hospital",
                "emergency": "yes",
                "healthcare": "hospital"
            },
            "geometry": {
                "type": "Point",
                "coordinates": [
                    21.23339241485241,
                    51.16543782713524
                ]
            }
        },
        {
            "type": "Feature",
            "properties": {
                "name": "Samodzielny Publiczny Zespół Zakładów Opieki Zdrowotnej W Pionkach",
                "website": "http://www.spzzozpionki.pl/",
                "phone": "48 612-13-81",
                "email": "spzzoz@spzzozpionki.pl",
                "amenity": "hospital",
                "emergency": "yes",
                "healthcare": "hospital"
            },
            "geometry": {
                "type": "Point",
                "coordinates": [
                    21.444766966442373,
                    51.475172399328535
                ]
            }
        }
    ]
}