{
    "type": "FeatureCollection",
    "name": "JPT_KOD_JE_2262",
    "features": [
        {
            "type": "Feature",
            "properties": {
                "name": "Uniwersyteckie Centrum Medycyny Morskiej I Tropikalnej",
                "website": "http://www.ucmmit.gdynia.pl",
                "phone": "58 699-85-06",
                "amenity": "hospital",
                "emergency": "yes",
                "healthcare": "hospital"
            },
            "geometry": {
                "type": "Point",
                "coordinates": [
                    18.54887034984809,
                    54.48748987289382
                ]
            }
        },
        {
            "type": "Feature",
            "properties": {
                "name": "Szpitale Pomorskie Sp. Z O.O.",
                "website": "http://www.szpitalepomorskie.eu",
                "phone": "224-800-800",
                "amenity": "hospital",
                "emergency": "yes",
                "healthcare": "hospital"
            },
            "geometry": {
                "type": "Point",
                "coordinates": [
                    18.553008461289128,
                    54.48962867444876
                ]
            }
        }
    ]
}