{
    "type": "FeatureCollection",
    "name": "JPT_KOD_JE_2811",
    "features": [
        {
            "type": "Feature",
            "properties": {
                "name": "Zespół Opieki Zdrowotnej W Nidzicy",
                "website": "https://www.zoz.nidzica.pl",
                "phone": "89 625 05 35 ",
                "amenity": "hospital",
                "emergency": "yes",
                "healthcare": "hospital"
            },
            "geometry": {
                "type": "Point",
                "coordinates": [
                    20.432503371812388,
                    53.35969768485364
                ]
            }
        }
    ]
}