{
    "type": "FeatureCollection",
    "name": "JPT_KOD_JE_3016",
    "features": [
        {
            "type": "Feature",
            "properties": {
                "name": "Samodzielny Publiczny Zakład Opieki Zdrowotnej W Obornikach",
                "website": "http://www.szpital.oborniki.info/ ",
                "phone": "(061)29-73-600 ",
                "amenity": "hospital",
                "emergency": "yes",
                "healthcare": "hospital"
            },
            "geometry": {
                "type": "Point",
                "coordinates": [
                    16.81596599905593,
                    52.653288764106975
                ]
            }
        }
    ]
}