{
    "type": "FeatureCollection",
    "name": "JPT_KOD_JE_1815",
    "features": [
        {
            "type": "Feature",
            "properties": {
                "name": "Zespół Opieki Zdrowotnej W Ropczycach",
                "website": "http://zozropczyce.pl",
                "phone": "+48 17 221 86 16",
                "amenity": "hospital",
                "emergency": "yes",
                "healthcare": "hospital"
            },
            "geometry": {
                "type": "Point",
                "coordinates": [
                    21.616023511870598,
                    50.05127857770651
                ]
            }
        }
    ]
}