{
    "type": "FeatureCollection",
    "name": "JPT_KOD_JE_1802",
    "features": [
        {
            "type": "Feature",
            "properties": {
                "_uid_": 545,
                "JPT_KOD_JE": "1802",
                "JPT_NAZWA_": "powiat brzozowski",
                "id": 291,
                "wojewodztwo": "podkarpackie",
                "miasto": "Brzozów",
                "powiat": "brzozowski ",
                "adres": "ks. Józefa Bielawskiego 18",
                "miejscowosc": "Brzozów",
                "kod": "36-200 ",
                "nazwa": "SZPITAL SPECJALISTYCZNY W BRZOZOWIE PODKARPACKI OŚRODEK ONKOLOGICZNY IM.KS.B.MARKIEWICZA",
                "poziom": "Szpital onkologiczny lub pulmonologiczny",
                "www": "http://szpital-brzozow.pl",
                "telefon": "(013)430 95 52",
                "e-mail": null
            },
            "geometry": {
                "type": "Point",
                "coordinates": [
                    22.024631986176654,
                    49.69255572377262
                ]
            }
        }
    ]
}