{
    "type": "FeatureCollection",
    "name": "JPT_KOD_JE_2408",
    "features": [
        {
            "type": "Feature",
            "properties": {
                "name": "Centrum Zdrowia W Mikołowie Sp. Z O.O.",
                "website": "http://www.szpital-mikolow.com.pl/index.php",
                "phone": "32 325 75 00",
                "amenity": "hospital",
                "emergency": "yes",
                "healthcare": "hospital"
            },
            "geometry": {
                "type": "Point",
                "coordinates": [
                    18.905115193279784,
                    50.17476598835844
                ]
            }
        },
        {
            "type": "Feature",
            "properties": {
                "name": "Szpital Św. Józefa Sp. Z O. O.",
                "website": "http://www.szpital.boromeuszki.org.pl/Strona",
                "phone": "32 226 59 77",
                "amenity": "hospital",
                "emergency": "yes",
                "healthcare": "hospital"
            },
            "geometry": {
                "type": "Point",
                "coordinates": [
                    18.908092486894898,
                    50.170124395459844
                ]
            }
        },
        {
            "type": "Feature",
            "properties": {
                "name": "Szpital Chorób Płuc",
                "website": "http://www.szpitalorzesze.pl",
                "phone": "32 221 36 61",
                "amenity": "hospital",
                "emergency": "yes",
                "healthcare": "hospital"
            },
            "geometry": {
                "type": "Point",
                "coordinates": [
                    18.77460845963099,
                    50.1502936955719
                ]
            }
        }
    ]
}