{
    "type": "FeatureCollection",
    "name": "JPT_KOD_JE_1212",
    "features": [
        {
            "type": "Feature",
            "properties": {
                "name": "Nowy Szpital W Olkuszu Spółka Z Ograniczoną Odpowiedzialnością",
                "website": "http://www.nowyszpital.pl/olkusz",
                "phone": "412401200",
                "amenity": "hospital",
                "emergency": "yes",
                "healthcare": "hospital"
            },
            "geometry": {
                "type": "Point",
                "coordinates": [
                    19.568624788243874,
                    50.2689521303806
                ]
            }
        },
        {
            "type": "Feature",
            "properties": {
                "name": "Wojewódzki Szpital Chorób Płuc I Rehabilitacji",
                "website": "http://www.wschp.pl",
                "phone": "32 642 80 90 wew. 58 ",
                "amenity": "hospital",
                "emergency": "yes",
                "healthcare": "hospital"
            },
            "geometry": {
                "type": "Point",
                "coordinates": [
                    19.61356561725988,
                    50.344589979697766
                ]
            }
        }
    ]
}