{
    "type": "FeatureCollection",
    "name": "JPT_KOD_JE_0861",
    "features": [
        {
            "type": "Feature",
            "properties": {
                "name": "Wielospecjalistyczny Szpital Wojewódzki W Gorzowie Wlkp. Spółka Z Ograniczoną Odpowiedzialnością",
                "website": "http://www.szpital.gorzow.pl",
                "phone": "95 733 12 00",
                "email": "sekretariat@szpital.gorzow.pl",
                "amenity": "hospital",
                "emergency": "yes",
                "healthcare": "hospital"
            },
            "geometry": {
                "type": "Point",
                "coordinates": [
                    15.235853420990566,
                    52.76224148781511
                ]
            }
        }
    ]
}