{
    "type": "FeatureCollection",
    "name": "JPT_KOD_JE_3029",
    "features": [
        {
            "type": "Feature",
            "properties": {
                "name": "Samodzielny Publiczny Zakład Opieki Zdrowotnej W Wolsztynie",
                "website": "https://www.spzozwolsztyn.pl/ ",
                "phone": "(068)34-77-300 ",
                "amenity": "hospital",
                "emergency": "yes",
                "healthcare": "hospital"
            },
            "geometry": {
                "type": "Point",
                "coordinates": [
                    16.117288383692053,
                    52.11668649796636
                ]
            }
        }
    ]
}