{
    "type": "FeatureCollection",
    "name": "JPT_KOD_JE_0221",
    "features": [
        {
            "type": "Feature",
            "properties": {
                "name": "Sanatoria Dolnośląskie Spółka Z Ograniczoną Odpowiedzialnością",
                "website": "http://www.sanatoria-dolnoslaskie.pl",
                "phone": "74 836 97 11",
                "email": "biuro.rosciszow@sanatoria-dolnoslaskie.pl",
                "amenity": "hospital",
                "emergency": "yes",
                "healthcare": "hospital"
            },
            "geometry": {
                "type": "Point",
                "coordinates": [
                    16.23619510619037,
                    50.68495382868706
                ]
            }
        }
    ]
}