{
    "type": "FeatureCollection",
    "name": "JPT_KOD_JE_3214",
    "features": [
        {
            "type": "Feature",
            "properties": {
                "name": "Samodzielny Publiczny Wielospecjalistyczny Zakład Opieki Zdrowotnej W Stargardzie",
                "website": "http://zozstargard.pl/ ",
                "phone": "91 577 63 55 ",
                "amenity": "hospital",
                "emergency": "yes",
                "healthcare": "hospital"
            },
            "geometry": {
                "type": "Point",
                "coordinates": [
                    15.036186297553266,
                    53.34281485148209
                ]
            }
        }
    ]
}