{
    "type": "FeatureCollection",
    "name": "JPT_KOD_JE_2470",
    "features": [
        {
            "type": "Feature",
            "properties": {
                "_uid_": 187,
                "JPT_KOD_JE": "2470",
                "JPT_NAZWA_": "powiat Mysłowice",
                "id": 518,
                "wojewodztwo": "śląskie",
                "miasto": "Mysłowice",
                "powiat": "Mysłowice",
                "adres": "Mikołowska 1",
                "miejscowosc": "Mysłowice",
                "kod": null,
                "nazwa": "Mysłowickie Centrum Zdrowia Spółka z ograniczoną odpowiedzialnością",
                "poziom": "I stopień",
                "www": "http://www.mcz.myslowice.pl",
                "telefon": "32 317 44 29",
                "e-mail": null
            },
            "geometry": {
                "type": "Point",
                "coordinates": [
                    19.137418839068513,
                    50.23975509273785
                ]
            }
        },
        {
            "type": "Feature",
            "properties": {
                "_uid_": 188,
                "JPT_KOD_JE": "2470",
                "JPT_NAZWA_": "powiat Mysłowice",
                "id": 522,
                "wojewodztwo": "śląskie",
                "miasto": "Mysłowice",
                "powiat": "Mysłowice",
                "adres": "Bytomska 41",
                "miejscowosc": "Mysłowice",
                "kod": null,
                "nazwa": "SP ZOZ Szpital Nr 2 im. dr. Tadeusza Boczonia w Mysłowicach",
                "poziom": "I stopień",
                "www": "http://www.szpital2myslowice.pl",
                "telefon": "723183348",
                "e-mail": null
            },
            "geometry": {
                "type": "Point",
                "coordinates": [
                    19.13299571652498,
                    50.247225433812304
                ]
            }
        }
    ]
}