{
    "type": "FeatureCollection",
    "name": "JPT_KOD_JE_1603",
    "features": [
        {
            "type": "Feature",
            "properties": {
                "name": "Samodzielny Publiczny Zespół Opieki Zdrowotnej W Kędzierzynie-Koźlu",
                "website": "http://www.e-szpital.eu",
                "phone": "77 406 25 00",
                "amenity": "hospital",
                "emergency": "yes",
                "healthcare": "hospital"
            },
            "geometry": {
                "type": "Point",
                "coordinates": [
                    18.151337560247672,
                    50.33243587417834
                ]
            }
        }
    ]
}