{
    "type": "FeatureCollection",
    "name": "JPT_KOD_JE_1821",
    "features": [
        {
            "type": "Feature",
            "properties": {
                "name": "Samodzielny Publiczny Zespół Opieki Zdrowotnej W Lesku",
                "website": "http://spzozlesko.pl",
                "phone": "(013)469 80 71",
                "amenity": "hospital",
                "emergency": "yes",
                "healthcare": "hospital"
            },
            "geometry": {
                "type": "Point",
                "coordinates": [
                    22.331839810939172,
                    49.473623247100804
                ]
            }
        }
    ]
}