{
    "type": "FeatureCollection",
    "name": "JPT_KOD_JE_3215",
    "features": [
        {
            "type": "Feature",
            "properties": {
                "name": "Szpital W Szczecinku Spółka Z O.O.",
                "website": "http://www.szpital.szczecinek.pl ",
                "phone": "94 374 33 33; 94 37 26 700 ",
                "amenity": "hospital",
                "emergency": "yes",
                "healthcare": "hospital"
            },
            "geometry": {
                "type": "Point",
                "coordinates": [
                    16.678675746713644,
                    53.7126800872687
                ]
            }
        }
    ]
}