{
    "type": "FeatureCollection",
    "name": "JPT_KOD_JE_3024",
    "features": [
        {
            "type": "Feature",
            "properties": {
                "name": "Samodzielny Publiczny Zakład Opieki Zdrowotnej",
                "website": "http://www.szamotuly.med.pl/ ",
                "phone": "(061)29-27-101 ",
                "amenity": "hospital",
                "emergency": "yes",
                "healthcare": "hospital"
            },
            "geometry": {
                "type": "Point",
                "coordinates": [
                    16.58122905110238,
                    52.61075266285635
                ]
            }
        }
    ]
}