{
    "type": "FeatureCollection",
    "name": "JPT_KOD_JE_3004",
    "features": [
        {
            "type": "Feature",
            "properties": {
                "name": "Samodzielny Publiczny Zespół Opieki Zdrowotnej W Gostyniu",
                "website": "http://www.szpitalgostyn.pl/ ",
                "phone": "(065)57-26-700 DO 04 ",
                "amenity": "hospital",
                "emergency": "yes",
                "healthcare": "hospital"
            },
            "geometry": {
                "type": "Point",
                "coordinates": [
                    17.010801162483933,
                    51.88273607493994
                ]
            }
        }
    ]
}