{
    "type": "FeatureCollection",
    "name": "JPT_KOD_JE_2402",
    "features": [
        {
            "type": "Feature",
            "properties": {
                "name": "Samodzielny Publiczny Zakład Opieki Zdrowotnej Szpital Kolejowy W Wilkowicach-Bystrej",
                "website": "http://www.szpital-kolejowy.com",
                "phone": "33 812 20 20",
                "amenity": "hospital",
                "emergency": "yes",
                "healthcare": "hospital"
            },
            "geometry": {
                "type": "Point",
                "coordinates": [
                    19.089739578357502,
                    49.77273292850357
                ]
            }
        },
        {
            "type": "Feature",
            "properties": {
                "name": "Centrum Pulmonologii I Torakochirurgii W Bystrej",
                "website": "http://www.szpitalbystra.pl",
                "phone": "33 499 18 01",
                "amenity": "hospital",
                "emergency": "yes",
                "healthcare": "hospital"
            },
            "geometry": {
                "type": "Point",
                "coordinates": [
                    19.07015498090162,
                    49.76548846817809
                ]
            }
        }
    ]
}