{
    "type": "FeatureCollection",
    "name": "JPT_KOD_JE_1804",
    "features": [
        {
            "type": "Feature",
            "properties": {
                "name": "Centrum Opieki Medycznej",
                "website": "http://comjar.pl",
                "phone": "(016)621 54 21",
                "amenity": "hospital",
                "emergency": "yes",
                "healthcare": "hospital"
            },
            "geometry": {
                "type": "Point",
                "coordinates": [
                    22.693790604653856,
                    50.01282443131865
                ]
            }
        }
    ]
}