{
    "type": "FeatureCollection",
    "name": "JPT_KOD_JE_0402",
    "features": [
        {
            "type": "Feature",
            "properties": {
                "name": "Zespół Opieki Zdrowotnej W Brodnicy",
                "website": "http://www.zozbrodnica.pl",
                "phone": "56 66 89 100",
                "amenity": "hospital",
                "emergency": "yes",
                "healthcare": "hospital"
            },
            "geometry": {
                "type": "Point",
                "coordinates": [
                    19.395773428412536,
                    53.261603230476325
                ]
            }
        }
    ]
}