{
    "type": "FeatureCollection",
    "name": "JPT_KOD_JE_1812",
    "features": [
        {
            "type": "Feature",
            "properties": {
                "name": "Samodzielny Publiczny Zespół Zakładów Opieki Zdrowotnej W Nisku",
                "website": "http://szpital-nisko.pl",
                "phone": "(015)841 67 03",
                "amenity": "hospital",
                "emergency": "yes",
                "healthcare": "hospital"
            },
            "geometry": {
                "type": "Point",
                "coordinates": [
                    22.142696554811373,
                    50.519545845238646
                ]
            }
        }
    ]
}