{
    "type": "FeatureCollection",
    "name": "JPT_KOD_JE_0261",
    "features": [
        {
            "type": "Feature",
            "properties": {
                "name": "Wojewódzkie Centrum Szpitalne Kotliny Jeleniogórskiej",
                "website": "http://www.spzoz.jgora.pl",
                "phone": "75 75 37 100",
                "email": "poczta@spzoz.jgora.pl",
                "amenity": "hospital",
                "emergency": "yes",
                "healthcare": "hospital"
            },
            "geometry": {
                "type": "Point",
                "coordinates": [
                    15.763546436106736,
                    50.91346776371448
                ]
            }
        }
    ]
}