{
    "type": "FeatureCollection",
    "name": "JPT_KOD_JE_1803",
    "features": [
        {
            "type": "Feature",
            "properties": {
                "name": "Zespół Opieki Zdrowotnej W Dębicy",
                "website": "http://zoz-debica.pl",
                "phone": "(014)670 30 20",
                "amenity": "hospital",
                "emergency": "yes",
                "healthcare": "hospital"
            },
            "geometry": {
                "type": "Point",
                "coordinates": [
                    21.393013194645576,
                    50.03910695530579
                ]
            }
        }
    ]
}