{
    "type": "FeatureCollection",
    "name": "JPT_KOD_JE_2063",
    "features": [
        {
            "type": "Feature",
            "properties": {
                "_uid_": 361,
                "JPT_KOD_JE": "2063",
                "JPT_NAZWA_": "powiat Suwałki",
                "id": 559,
                "wojewodztwo": "podlaskie",
                "miasto": "m. Suwałki",
                "powiat": "Suwałki",
                "adres": "Szpitalna 60",
                "miejscowosc": "Suwałki",
                "kod": "16-400",
                "nazwa": "SZPITAL WOJEWÓDZKI IM. DR. L. RYDYGIERA W SUWAŁKACH",
                "poziom": "II stopień",
                "www": "http://www.szpital.suwalki.pl",
                "telefon": "87 562 94 21 ",
                "e-mail": null
            },
            "geometry": {
                "type": "Point",
                "coordinates": [
                    22.92482041236954,
                    54.118828109840535
                ]
            }
        }
    ]
}