{
    "type": "FeatureCollection",
    "name": "JPT_KOD_JE_3015",
    "features": [
        {
            "type": "Feature",
            "properties": {
                "name": "Samodzielny Publiczny Zakład Opieki Zdrowotnej Imienia Doktora Kazimierza Hołogi",
                "website": "http://www.szpital-nowytomysl.pl/ ",
                "phone": "(061)44-27-300 ",
                "amenity": "hospital",
                "emergency": "yes",
                "healthcare": "hospital"
            },
            "geometry": {
                "type": "Point",
                "coordinates": [
                    16.138598014369872,
                    52.315971582381216
                ]
            }
        }
    ]
}