{
    "type": "FeatureCollection",
    "name": "JPT_KOD_JE_1211",
    "features": [
        {
            "type": "Feature",
            "properties": {
                "name": "Podhalański Szpital Specjalistyczny Im. Jana Pawła Ii W Nowym Targu",
                "website": "http://www.pszs.eu",
                "phone": "18 26 33 000",
                "amenity": "hospital",
                "emergency": "yes",
                "healthcare": "hospital"
            },
            "geometry": {
                "type": "Point",
                "coordinates": [
                    20.027370727464,
                    49.48976171712866
                ]
            }
        },
        {
            "type": "Feature",
            "properties": {
                "name": "Instytut Gruźlicy I Chorób Płuc",
                "website": "http://www.zpigichp.edu.pl",
                "phone": "18 267 60 60",
                "amenity": "hospital",
                "emergency": "yes",
                "healthcare": "hospital"
            },
            "geometry": {
                "type": "Point",
                "coordinates": [
                    19.967467692211642,
                    49.60471050421543
                ]
            }
        }
    ]
}