{
    "type": "FeatureCollection",
    "name": "JPT_KOD_JE_3203",
    "features": [
        {
            "type": "Feature",
            "properties": {
                "name": "\"Szpitale Polskie\" Spółka Akcyjna",
                "website": "http://szpitale-polskie.pl/SPSA/drawsko/ ",
                "phone": "94 36 30 341 ",
                "amenity": "hospital",
                "emergency": "yes",
                "healthcare": "hospital"
            },
            "geometry": {
                "type": "Point",
                "coordinates": [
                    15.81104100563643,
                    53.52481843214359
                ]
            }
        }
    ]
}
