{
    "type": "FeatureCollection",
    "name": "JPT_KOD_JE_3263",
    "features": [
        {
            "type": "Feature",
            "properties": {
                "name": "Szpital Miejski Im. Jana Garduły W Świnoujściu",
                "website": "https://szpital-swinoujscie.pl/ ",
                "phone": "91 32 67 424, 91 32 67 322; po godz. 20.00 tel. 91 32 67 337 ",
                "amenity": "hospital",
                "emergency": "yes",
                "healthcare": "hospital"
            },
            "geometry": {
                "type": "Point",
                "coordinates": [
                    14.258504316839787,
                    53.90999458995793
                ]
            }
        }
    ]
}
