{
    "type": "FeatureCollection",
    "name": "JPT_KOD_JE_0801",
    "features": [
        {
            "type": "Feature",
            "properties": {
                "name": "Nowy Szpital W Kostrzynie Nad Odrą Spółka Z Ograniczoną Odpowiedzialnością",
                "website": "http://www.nowyszpital.pl",
                "phone": "41 240 19 00",
                "email": "kostrzyn@nowyszpital.pl",
                "amenity": "hospital",
                "emergency": "yes",
                "healthcare": "hospital"
            },
            "geometry": {
                "type": "Point",
                "coordinates": [
                    14.641400105358022,
                    52.60812271636903
                ]
            }
        }
    ]
}