{
    "type": "FeatureCollection",
    "name": "JPT_KOD_JE_2861",
    "crs": {
        "type": "name",
        "properties": {
            "name": "urn:ogc:def:crs:EPSG::4326"
        }
    },
    "features": [
        {
            "type": "Feature",
            "properties": {
                "gid": 187,
                "JPT_KOD_JE": "2861",
                "JPT_NAZWA_": "powiat Elbląg",
                "id": "104#445",
                "krotka_nazwa_oddz_nfz": "WARMIŃSKO-MAZURSKI OW NFZ",
                "kod_swiadczeniodawcy": "140000551",
                "swiadczeniodawca": "Wojewódzki Szpital Zespolony w Elblągu",
                "miejscowosc": "Elbląg",
                "ulica": "Królewiecka ",
                "numer_domu": "146",
                "adres_swiadczeniodawcy": "Królewiecka 146",
                "telefon": "55 239 58 11; \r\n55 236 89 99",
                "dodatkowe_miejsce": "-",
                "dodatkowe_informacje": "-",
                "g_traf": 1.0,
                "g_ilosc": 1,
                "g_ul": "Królewiecka",
                "g_miejsc": "Elbląg",
                "g_adr": "146",
                "g_teryt": "2861011",
                "g_gm": "Elbląg",
                "g_pow": "Elbląg",
                "g_woj": "warmińsko-mazurskie",
                "g_szer": 19.429103022480817,
                "g_dlug": 54.17936372725805,
                "g_uuid": "999ff735-1353-4782-9200-a07f64ea4950",
                "g_edycja": null
            },
            "geometry": {
                "type": "Point",
                "coordinates": [
                    19.429100000000194,
                    54.179360000019045
                ]
            }
        },
        {
            "type": "Feature",
            "properties": {
                "gid": 521,
                "JPT_KOD_JE": "2861",
                "JPT_NAZWA_": "powiat Elbląg",
                "id": "104#446",
                "krotka_nazwa_oddz_nfz": "WARMIŃSKO-MAZURSKI OW NFZ",
                "kod_swiadczeniodawcy": "140000158",
                "swiadczeniodawca": "Szpital Miejski Św. Jana Pawła II w Elblągu                                                                                      ( porady  w trybie wyjazdowym )",
                "miejscowosc": "Elbląg",
                "ulica": " Żeromskiego ",
                "numer_domu": "22",
                "adres_swiadczeniodawcy": " Żeromskiego 22",
                "telefon": "55 230 42 28",
                "dodatkowe_miejsce": "-",
                "dodatkowe_informacje": "-",
                "g_traf": 1.0,
                "g_ilosc": 1,
                "g_ul": "Żeromskiego Stefana",
                "g_miejsc": "Elbląg",
                "g_adr": "22",
                "g_teryt": "2861011",
                "g_gm": "Elbląg",
                "g_pow": "Elbląg",
                "g_woj": "warmińsko-mazurskie",
                "g_szer": 19.421942411923034,
                "g_dlug": 54.15733089821162,
                "g_uuid": "879ddaaf-d9f0-47d7-9a95-a40ab9703edc",
                "g_edycja": null
            },
            "geometry": {
                "type": "Point",
                "coordinates": [
                    19.421940000000195,
                    54.157330000019016
                ]
            }
        }
    ]
}