{
    "type": "FeatureCollection",
    "name": "JPT_KOD_JE_0803",
    "crs": {
        "type": "name",
        "properties": {
            "name": "urn:ogc:def:crs:EPSG::4326"
        }
    },
    "features": [
        {
            "type": "Feature",
            "properties": {
                "gid": 19,
                "JPT_KOD_JE": "0803",
                "JPT_NAZWA_": "powiat międzyrzecki",
                "id": "104#98",
                "krotka_nazwa_oddz_nfz": "LUBUSKI OW NFZ",
                "kod_swiadczeniodawcy": "100324",
                "swiadczeniodawca": "Niepubliczny Zakład Opieki Zdrowotnej Szpital im.dr n.med.Radzimira Śmigielskiego",
                "miejscowosc": "Skwierzyna\r\n",
                "ulica": " Szpitalna ",
                "numer_domu": "5",
                "adres_swiadczeniodawcy": " Szpitalna 5",
                "telefon": "95 717 00 39 wew. 10",
                "dodatkowe_miejsce": "-",
                "dodatkowe_informacje": "-",
                "g_traf": 1.0,
                "g_ilosc": 1,
                "g_ul": "Szpitalna",
                "g_miejsc": "Skwierzyna",
                "g_adr": "5",
                "g_teryt": "0803053",
                "g_gm": "Skwierzyna",
                "g_pow": "międzyrzecki",
                "g_woj": "lubuskie",
                "g_szer": 15.50655149117082,
                "g_dlug": 52.59396092671863,
                "g_uuid": "9ffc8ded-0942-4878-b2ba-70db49b5a238",
                "g_edycja": null
            },
            "geometry": {
                "type": "Point",
                "coordinates": [
                    15.506549999965896,
                    52.59396000001693
                ]
            }
        },
        {
            "type": "Feature",
            "properties": {
                "gid": 123,
                "JPT_KOD_JE": "0803",
                "JPT_NAZWA_": "powiat międzyrzecki",
                "id": "104#96",
                "krotka_nazwa_oddz_nfz": "LUBUSKI OW NFZ",
                "kod_swiadczeniodawcy": "040184",
                "swiadczeniodawca": "Szpital Międzyrzecki Sp. z o.o.",
                "miejscowosc": "Międzyrzecz\r\n",
                "ulica": "Konstytucji 3 Maja ",
                "numer_domu": "35",
                "adres_swiadczeniodawcy": "Konstytucji 3-Maja 35",
                "telefon": "504,231,614",
                "dodatkowe_miejsce": "-",
                "dodatkowe_informacje": "-",
                "g_traf": 1.0,
                "g_ilosc": 1,
                "g_ul": "Konstytucji 3 Maja",
                "g_miejsc": "Międzyrzecz",
                "g_adr": "35",
                "g_teryt": "0803023",
                "g_gm": "Międzyrzecz",
                "g_pow": "międzyrzecki",
                "g_woj": "lubuskie",
                "g_szer": 15.5841776987145,
                "g_dlug": 52.44035948897494,
                "g_uuid": "1026a0e8-ddb8-4e9d-bd92-8ca9031f5408",
                "g_edycja": null
            },
            "geometry": {
                "type": "Point",
                "coordinates": [
                    15.584179999968747,
                    52.44036000001658
                ]
            }
        }
    ]
}