{
    "type": "FeatureCollection",
    "name": "JPT_KOD_JE_0224",
    "crs": {
        "type": "name",
        "properties": {
            "name": "urn:ogc:def:crs:EPSG::4326"
        }
    },
    "features": [
        {
            "type": "Feature",
            "properties": {
                "gid": 112,
                "JPT_KOD_JE": "0224",
                "JPT_NAZWA_": "powiat ząbkowicki",
                "id": "104#34",
                "krotka_nazwa_oddz_nfz": "DOLNOŚLĄSKI OW NFZ",
                "kod_swiadczeniodawcy": "3202053",
                "swiadczeniodawca": "Szpital Św.Antoniego w Ząbkowicach Śląskich",
                "miejscowosc": "Ząbkowice Śląskie\r\n",
                "ulica": "Bolesława Chrobrego ",
                "numer_domu": "5",
                "adres_swiadczeniodawcy": "Bolesława Chrobrego 5",
                "telefon": "Ząbkowice: 74 64 13 410; 72 76 00 374; Ziębice: 74 819 12 99 ",
                "dodatkowe_miejsce": " pl. Strażacki 8; 57-220 Ziębice",
                "dodatkowe_informacje": "-",
                "g_traf": 1.0,
                "g_ilosc": 1,
                "g_ul": "Bolesława Chrobrego",
                "g_miejsc": "Ząbkowice Śląskie",
                "g_adr": "5",
                "g_teryt": "0224053",
                "g_gm": "Ząbkowice Śląskie",
                "g_pow": "ząbkowicki",
                "g_woj": "dolnośląskie",
                "g_szer": 16.817134865274934,
                "g_dlug": 50.58751934408964,
                "g_uuid": "9ca841c7-b1c9-4535-b592-40fe94d196b1",
                "g_edycja": null
            },
            "geometry": {
                "type": "Point",
                "coordinates": [
                    16.81712999999547,
                    50.58752000001335
                ]
            }
        }
    ]
}