{
    "type": "FeatureCollection",
    "name": "JPT_KOD_JE_1816",
    "features": [
        {
            "type": "Feature",
            "properties": {
                "gid": 160,
                "JPT_KOD_JE": "1816",
                "JPT_NAZWA_": "powiat rzeszowski",
                "id": "104#281",
                "krotka_nazwa_oddz_nfz": "PODKARPACKI OW NFZ",
                "kod_swiadczeniodawcy": "09R/031114",
                "swiadczeniodawca": "Nowe Techniki Medyczne Szpital Specjalistyczny  im. ŚWIĘTEJ RODZINY Sp. z o.o. Rudna Mała",
                "miejscowosc": "Rudna Mała",
                "ulica": "Rudna Mała ",
                "numer_domu": "600",
                "adres_swiadczeniodawcy": "Rudna Mała 600",
                "telefon": "17 866 99 29",
                "dodatkowe_miejsce": "-",
                "dodatkowe_informacje": "-",
                "g_traf": 1.0,
                "g_ilosc": 1,
                "g_ul": "",
                "g_miejsc": "",
                "g_adr": "",
                "g_teryt": "",
                "g_gm": "",
                "g_pow": "",
                "g_woj": "",
                "g_szer": 21.97860700770169,
                "g_dlug": 50.10479852326768,
                "g_uuid": "f21bb799-7e87-4bec-a544-51dfdf860f78",
                "g_edycja": 1
            },
            "geometry": {
                "type": "Point",
                "coordinates": [
                    21.97861000002097,
                    50.10480000001277
                ]
            }
        },
        {
            "type": "Feature",
            "properties": {
                "gid": 260,
                "JPT_KOD_JE": "1816",
                "JPT_NAZWA_": "powiat rzeszowski",
                "id": "104#280",
                "krotka_nazwa_oddz_nfz": "PODKARPACKI OW NFZ",
                "kod_swiadczeniodawcy": "09R/010018",
                "swiadczeniodawca": "Zespół Opieki Zdrowotnej Nr 2 w Rzeszowie",
                "miejscowosc": "Dynów ",
                "ulica": "ks. Ożoga ",
                "numer_domu": "32",
                "adres_swiadczeniodawcy": "ks. Ożoga 32",
                "telefon": "16 652 10 35",
                "dodatkowe_miejsce": "-",
                "dodatkowe_informacje": "-",
                "g_traf": 1.0,
                "g_ilosc": 1,
                "g_ul": "Ks. Ożoga Józefa",
                "g_miejsc": "Dynów",
                "g_adr": "32",
                "g_teryt": "1816011",
                "g_gm": "Dynów",
                "g_pow": "rzeszowski",
                "g_woj": "podkarpackie",
                "g_szer": 22.223323201473253,
                "g_dlug": 49.8141779492236,
                "g_uuid": "9125b895-e489-4dd9-8251-b9ebfc28564f",
                "g_edycja": null
            },
            "geometry": {
                "type": "Point",
                "coordinates": [
                    22.223320000032203,
                    49.81418000001247
                ]
            }
        },
        {
            "type": "Feature",
            "properties": {
                "gid": 265,
                "JPT_KOD_JE": "1816",
                "JPT_NAZWA_": "powiat rzeszowski",
                "id": "104#301",
                "krotka_nazwa_oddz_nfz": "PODKARPACKI OW NFZ",
                "kod_swiadczeniodawcy": "09R/010018",
                "swiadczeniodawca": "Zespół Opieki Zdrowotnej Nr 2 w Rzeszowie",
                "miejscowosc": "Sokołów Małopolski  ",
                "ulica": "1000-lecia ",
                "numer_domu": "4",
                "adres_swiadczeniodawcy": "1000 - Lecia 4",
                "telefon": "17 772 90 17",
                "dodatkowe_miejsce": "-",
                "dodatkowe_informacje": "-",
                "g_traf": 1.0,
                "g_ilosc": 1,
                "g_ul": "",
                "g_miejsc": "",
                "g_adr": "",
                "g_teryt": "",
                "g_gm": "",
                "g_pow": "",
                "g_woj": "",
                "g_szer": 22.12219854708633,
                "g_dlug": 50.23349869031093,
                "g_uuid": "4e840291-4ab9-414e-abdf-dc0fbed58b91",
                "g_edycja": 1
            },
            "geometry": {
                "type": "Point",
                "coordinates": [
                    22.12220000002619,
                    50.233500000013024
                ]
            }
        }
    ]
}