{
    "type": "FeatureCollection",
    "name": "JPT_KOD_JE_2461",
    "features": [
        {
            "type": "Feature",
            "properties": {
                "gid": 384,
                "JPT_KOD_JE": "2461",
                "JPT_NAZWA_": "powiat Bielsko-Biała",
                "id": "104#359",
                "krotka_nazwa_oddz_nfz": "ŚLĄSKI OW NFZ",
                "kod_swiadczeniodawcy": "122/100069",
                "swiadczeniodawca": "Szpital Wojewódzki w Bielsku-Białej",
                "miejscowosc": "Bielsko-Biała",
                "ulica": "Al. Armii Krajowej ",
                "numer_domu": "101",
                "adres_swiadczeniodawcy": "Al. Armii Krajowej 101",
                "telefon": "33 506 58 58;",
                "dodatkowe_miejsce": "-",
                "dodatkowe_informacje": "-",
                "g_traf": 0.9,
                "g_ilosc": 1,
                "g_ul": "Aleja  Armii Krajowej",
                "g_miejsc": "Bielsko-Biała",
                "g_adr": "101",
                "g_teryt": "2461011",
                "g_gm": "Bielsko-Biała",
                "g_pow": "Bielsko-Biała",
                "g_woj": "śląskie",
                "g_szer": 19.038693997641513,
                "g_dlug": 49.792608398063116,
                "g_uuid": "00f4f2ae-47ca-48ca-8155-b4505401ec42",
                "g_edycja": null
            },
            "geometry": {
                "type": "Point",
                "coordinates": [
                    19.03869000000001,
                    49.79261000001222
                ]
            }
        },
        {
            "type": "Feature",
            "properties": {
                "gid": 385,
                "JPT_KOD_JE": "2461",
                "JPT_NAZWA_": "powiat Bielsko-Biała",
                "id": "104#360",
                "krotka_nazwa_oddz_nfz": "ŚLĄSKI OW NFZ",
                "kod_swiadczeniodawcy": "122/100333",
                "swiadczeniodawca": "Szpital Pediatryczny w Bielsku-Białej",
                "miejscowosc": "Bielsko-Biała",
                "ulica": "Sobieskiego   ",
                "numer_domu": "83",
                "adres_swiadczeniodawcy": "Sobieskiego 83  ",
                "telefon": "rejestracja: 33 828 40 02, dyżurka lekarska: 33 828 40 49",
                "dodatkowe_miejsce": "-",
                "dodatkowe_informacje": "-",
                "g_traf": 1.0,
                "g_ilosc": 1,
                "g_ul": "Jana Sobieskiego",
                "g_miejsc": "Bielsko-Biała",
                "g_adr": "83",
                "g_teryt": "2461011",
                "g_gm": "Bielsko-Biała",
                "g_pow": "Bielsko-Biała",
                "g_woj": "śląskie",
                "g_szer": 19.028795334802954,
                "g_dlug": 49.820998795305805,
                "g_uuid": "aa7fa908-1c54-4d1a-a310-dd3589996a00",
                "g_edycja": null
            },
            "geometry": {
                "type": "Point",
                "coordinates": [
                    19.028800000000007,
                    49.82100000001224
                ]
            }
        }
    ]
}